LICENSE
MANIFEST.in
README.md
autoargs.py
setup.py
autoargs.egg-info/PKG-INFO
autoargs.egg-info/SOURCES.txt
autoargs.egg-info/dependency_links.txt
autoargs.egg-info/top_level.txt