Metadata-Version: 1.1
Name: autoargs
Version: 0.0.2
Summary: Automatic Arg parsing
Home-page: https://github.com/metaperture/autoargs
Author: Michael Tartre
Author-email: metaperture@gmail.com
License: BSD 3-Clause
Platform: UNKNOWN
Classifier: Programming Language :: Python :: 3 :: Only
Classifier: Programming Language :: Python :: 3.3
Classifier: Programming Language :: Python :: 3.4
Classifier: Programming Language :: Python :: 3.5
Classifier: Programming Language :: Python :: 3.6
Classifier: Intended Audience :: Developers
Classifier: License :: OSI Approved :: BSD License
Classifier: Topic :: Software Development :: Libraries
Classifier: Topic :: Utilities
Classifier: Development Status :: 3 - Alpha
Classifier: Operating System :: OS Independent
Classifier: Topic :: Software Development
Classifier: Topic :: Software Development :: Code Generators
Classifier: Topic :: Software Development :: User Interfaces
Classifier: Topic :: System :: Shells
